_runtime.abi3.so
koi/decode.py
koi/utils.py
koi/build.py
koi/lstm.py
koi/__init__.py
koi/test/__init__.py
koi/test/test_lstm.py
koi_cuda102.libs/lib-cbd3474e.so
koi_cuda102-0.0.5.dist-info/WHEEL
koi_cuda102-0.0.5.dist-info/METADATA
koi_cuda102-0.0.5.dist-info/RECORD
koi_cuda102-0.0.5.dist-info/top_level.txt
